LICENSE
MANIFEST.in
README.md
requirements.txt
setup.py
bin/jira-info
jirainfo/__init__.py
jirainfo/cli.py
jirainfo/helpers.py
jirainfo/jirahelper.py
jirainfo.egg-info/PKG-INFO
jirainfo.egg-info/SOURCES.txt
jirainfo.egg-info/dependency_links.txt
jirainfo.egg-info/requires.txt
jirainfo.egg-info/top_level.txt
jirainfo/templates/__init__.py
jirainfo/templates/changelog.md
jirainfo/templates/email.html