Metadata-Version: 1.0
Name: jirainfo
Version: 0.2.0
Summary: UNKNOWN
Home-page: UNKNOWN
Author: Sebastian Ruml
Author-email: sebastian@sebastianruml.name
License: The MIT License (MIT)
